advanced/databases/__init__.py
advanced/databases/_src/__init__.py
advanced/databases/_src/big_list.py
advanced/databases/_src/big_sorted_set.py
advanced/databases/_src/index.py
advanced/databases/_src/mutable_sequence_islice.py
advanced/databases/_src/mutable_sequence_islice_proxy.py
advanced/databases/_src/sequence_islice.py
advanced/databases/_src/sequence_islice_proxy.py
advanced/databases/_src/viewable_mutable_sequence.py
advanced/databases/_src/viewable_sequence.py
advanced_databases-0.2.0.dist-info/LICENSE
advanced_databases-0.2.0.dist-info/METADATA
advanced_databases-0.2.0.dist-info/WHEEL
advanced_databases-0.2.0.dist-info/top_level.txt
advanced_databases-0.2.0.dist-info/RECORD
